{"nodes": [{"id": "e_base_mono_repo_template_mono_repo_packages_schemas_src_db_files_ts", "label": "files.ts", "file_type": "code", "source_file": "E:\\base-mono-repo\\template-mono-repo\\packages\\schemas\\src\\db\\files.ts", "source_location": "L1"}, {"id": "db_files_file", "label": "file", "file_type": "code", "source_file": "E:\\base-mono-repo\\template-mono-repo\\packages\\schemas\\src\\db\\files.ts", "source_location": "L4"}], "edges": [{"source": "e_base_mono_repo_template_mono_repo_packages_schemas_src_db_files_ts", "target": "pg_core", "relation": "imports_from", "context": "import", "confidence": "EXTRACTED", "source_file": "E:\\base-mono-repo\\template-mono-repo\\packages\\schemas\\src\\db\\files.ts", "source_location": "L1", "weight": 1.0}, {"source": "e_base_mono_repo_template_mono_repo_packages_schemas_src_db_files_ts", "target": "e_base_mono_repo_template_mono_repo_packages_schemas_src_db_users_ts", "relation": "imports_from", "context": "import", "confidence": "EXTRACTED", "source_file": "E:\\base-mono-repo\\template-mono-repo\\packages\\schemas\\src\\db\\files.ts", "source_location": "L2", "weight": 1.0}, {"source": "e_base_mono_repo_template_mono_repo_packages_schemas_src_db_files_ts", "target": "db_users_user", "relation": "imports", "context": "import", "confidence": "EXTRACTED", "source_file": "E:\\base-mono-repo\\template-mono-repo\\packages\\schemas\\src\\db\\files.ts", "source_location": "L2", "weight": 1.0}, {"source": "e_base_mono_repo_template_mono_repo_packages_schemas_src_db_files_ts", "target": "db_files_file", "relation": "contains", "confidence": "EXTRACTED", "source_file": "E:\\base-mono-repo\\template-mono-repo\\packages\\schemas\\src\\db\\files.ts", "source_location": "L4", "weight": 1.0}], "raw_calls": []}